winzy_get_the_file/__init__.py
winzy_get_the_file/app.py
winzy_get_the_file-0.0.1.dist-info/licenses/LICENSE
winzy_get_the_file-0.0.1.dist-info/METADATA
winzy_get_the_file-0.0.1.dist-info/WHEEL
winzy_get_the_file-0.0.1.dist-info/entry_points.txt
winzy_get_the_file-0.0.1.dist-info/top_level.txt
winzy_get_the_file-0.0.1.dist-info/RECORD
