Metadata-Version: 2.4
Name: winzy-get-the-file
Version: 0.0.1
Summary: Get files from a folder 
Author: Sukhbinder Singh
License: Apache-2.0
Project-URL: Homepage, https://github.com/sukhbinder/winzy-get-the-file
Project-URL: Changelog, https://github.com/sukhbinder/winzy-get-the-file/releases
Project-URL: Issues, https://github.com/sukhbinder/winzy-get-the-file/issues
Project-URL: CI, https://github.com/sukhbinder/winzy-get-the-file/actions
Classifier: License :: OSI Approved :: Apache Software License
License-File: LICENSE
Requires-Dist: winzy
Provides-Extra: test
Requires-Dist: pytest; extra == "test"
Dynamic: license-file
